{
  "query": "SELECT id, name, code, clientName FROM projects WHERE name LIKE '%vitest%' OR name LIKE '%测试%' OR name LIKE '%Test%' OR name = '' OR name IS NULL ORDER BY id;",
  "command": "mysql --batch --raw --column-names --default-character-set=utf8mb4 --host gateway04.us-east-1.prod.aws.tidbcloud.com --port 4000 --user 33Tk1DtnuVXRkg9.f5fe13a67640 --database fRco6A2SeYp4EEqicyDKLT --execute SELECT id, name, code, clientName FROM projects WHERE name LIKE '%vitest%' OR name LIKE '%测试%' OR name LIKE '%Test%' OR name = '' OR name IS NULL ORDER BY id;",
  "rows": [
    {
      "id": "1",
      "name": "Test Project 1773068866475",
      "code": "TP-001",
      "clientName": "Test Client"
    },
    {
      "id": "2",
      "name": "GetById Test 1773068866727",
      "code": "NULL",
      "clientName": "NULL"
    },
    {
      "id": "5",
      "name": "Task Test Project 1773068869553",
      "code": "NULL",
      "clientName": "NULL"
    },
    {
      "id": "6",
      "name": "Task Test Project 1773068870025",
      "code": "NULL",
      "clientName": "NULL"
    },
    {
      "id": "7",
      "name": "Task Test Project 1773068870517",
      "code": "NULL",
      "clientName": "NULL"
    },
    {
      "id": "8",
      "name": "Task Test Project 1773068870757",
      "code": "NULL",
      "clientName": "NULL"
    },
    {
      "id": "9",
      "name": "Task Test Project 1773068871487",
      "code": "NULL",
      "clientName": "NULL"
    },
    {
      "id": "10",
      "name": "Doc Test Project 1773068872439",
      "code": "NULL",
      "clientName": "NULL"
    },
    {
      "id": "11",
      "name": "Doc Test Project 1773068872916",
      "code": "NULL",
      "clientName": "NULL"
    },
    {
      "id": "12",
      "name": "Doc Test Project 1773068873413",
      "code": "NULL",
      "clientName": "NULL"
    },
    {
      "id": "13",
      "name": "Test Project 1773070380255",
      "code": "TP-001",
      "clientName": "Test Client"
    },
    {
      "id": "14",
      "name": "GetById Test 1773070380495",
      "code": "NULL",
      "clientName": "NULL"
    },
    {
      "id": "17",
      "name": "Task Test Project 1773070383282",
      "code": "NULL",
      "clientName": "NULL"
    },
    {
      "id": "18",
      "name": "Task Test Project 1773070383755",
      "code": "NULL",
      "clientName": "NULL"
    },
    {
      "id": "19",
      "name": "Task Test Project 1773070384231",
      "code": "NULL",
      "clientName": "NULL"
    },
    {
      "id": "20",
      "name": "Task Test Project 1773070384470",
      "code": "NULL",
      "clientName": "NULL"
    },
    {
      "id": "21",
      "name": "Task Test Project 1773070385183",
      "code": "NULL",
      "clientName": "NULL"
    },
    {
      "id": "22",
      "name": "Doc Test Project 1773070386131",
      "code": "NULL",
      "clientName": "NULL"
    },
    {
      "id": "23",
      "name": "Doc Test Project 1773070386599",
      "code": "NULL",
      "clientName": "NULL"
    },
    {
      "id": "24",
      "name": "Doc Test Project 1773070387073",
      "code": "NULL",
      "clientName": "NULL"
    },
    {
      "id": "25",
      "name": "Test Project 1773070535847",
      "code": "TP-001",
      "clientName": "Test Client"
    },
    {
      "id": "26",
      "name": "GetById Test 1773070536096",
      "code": "NULL",
      "clientName": "NULL"
    },
    {
      "id": "29",
      "name": "Task Test Project 1773070539011",
      "code": "NULL",
      "clientName": "NULL"
    },
    {
      "id": "30",
      "name": "Task Test Project 1773070539496",
      "code": "NULL",
      "clientName": "NULL"
    },
    {
      "id": "31",
      "name": "Task Test Project 1773070539989",
      "code": "NULL",
      "clientName": "NULL"
    },
    {
      "id": "32",
      "name": "Task Test Project 1773070540237",
      "code": "NULL",
      "clientName": "NULL"
    },
    {
      "id": "33",
      "name": "Task Test Project 1773070540974",
      "code": "NULL",
      "clientName": "NULL"
    },
    {
      "id": "34",
      "name": "Doc Test Project 1773070541951",
      "code": "NULL",
      "clientName": "NULL"
    },
    {
      "id": "35",
      "name": "Doc Test Project 1773070542435",
      "code": "NULL",
      "clientName": "NULL"
    },
    {
      "id": "36",
      "name": "Doc Test Project 1773070542930",
      "code": "NULL",
      "clientName": "NULL"
    },
    {
      "id": "37",
      "name": "Test Project 1773072459505",
      "code": "TP-001",
      "clientName": "Test Client"
    },
    {
      "id": "38",
      "name": "GetById Test 1773072459758",
      "code": "NULL",
      "clientName": "NULL"
    },
    {
      "id": "41",
      "name": "Task Test Project 1773072462667",
      "code": "NULL",
      "clientName": "NULL"
    },
    {
      "id": "42",
      "name": "Task Test Project 1773072463151",
      "code": "NULL",
      "clientName": "NULL"
    },
    {
      "id": "43",
      "name": "Task Test Project 1773072463646",
      "code": "NULL",
      "clientName": "NULL"
    },
    {
      "id": "44",
      "name": "Task Test Project 1773072463895",
      "code": "NULL",
      "clientName": "NULL"
    },
    {
      "id": "45",
      "name": "Task Test Project 1773072464636",
      "code": "NULL",
      "clientName": "NULL"
    },
    {
      "id": "46",
      "name": "Doc Test Project 1773072465625",
      "code": "NULL",
      "clientName": "NULL"
    },
    {
      "id": "47",
      "name": "Doc Test Project 1773072466114",
      "code": "NULL",
      "clientName": "NULL"
    },
    {
      "id": "48",
      "name": "Doc Test Project 1773072466625",
      "code": "NULL",
      "clientName": "NULL"
    },
    {
      "id": "49",
      "name": "Test Project 1773072529749",
      "code": "TP-001",
      "clientName": "Test Client"
    },
    {
      "id": "50",
      "name": "GetById Test 1773072529990",
      "code": "NULL",
      "clientName": "NULL"
    },
    {
      "id": "53",
      "name": "Task Test Project 1773072532779",
      "code": "NULL",
      "clientName": "NULL"
    },
    {
      "id": "54",
      "name": "Task Test Project 1773072533246",
      "code": "NULL",
      "clientName": "NULL"
    },
    {
      "id": "55",
      "name": "Task Test Project 1773072533760",
      "code": "NULL",
      "clientName": "NULL"
    },
    {
      "id": "56",
      "name": "Task Test Project 1773072533999",
      "code": "NULL",
      "clientName": "NULL"
    },
    {
      "id": "57",
      "name": "Task Test Project 1773072534710",
      "code": "NULL",
      "clientName": "NULL"
    },
    {
      "id": "58",
      "name": "Doc Test Project 1773072535650",
      "code": "NULL",
      "clientName": "NULL"
    },
    {
      "id": "59",
      "name": "Doc Test Project 1773072536117",
      "code": "NULL",
      "clientName": "NULL"
    },
    {
      "id": "60",
      "name": "Doc Test Project 1773072536596",
      "code": "NULL",
      "clientName": "NULL"
    },
    {
      "id": "61",
      "name": "Test Project 1773074286220",
      "code": "TP-001",
      "clientName": "Test Client"
    },
    {
      "id": "62",
      "name": "GetById Test 1773074286458",
      "code": "NULL",
      "clientName": "NULL"
    },
    {
      "id": "65",
      "name": "Task Test Project 1773074289210",
      "code": "NULL",
      "clientName": "NULL"
    },
    {
      "id": "66",
      "name": "Task Test Project 1773074289668",
      "code": "NULL",
      "clientName": "NULL"
    },
    {
      "id": "67",
      "name": "Task Test Project 1773074290139",
      "code": "NULL",
      "clientName": "NULL"
    },
    {
      "id": "68",
      "name": "Task Test Project 1773074290373",
      "code": "NULL",
      "clientName": "NULL"
    },
    {
      "id": "69",
      "name": "Task Test Project 1773074291080",
      "code": "NULL",
      "clientName": "NULL"
    },
    {
      "id": "70",
      "name": "Doc Test Project 1773074292014",
      "code": "NULL",
      "clientName": "NULL"
    },
    {
      "id": "71",
      "name": "Doc Test Project 1773074292504",
      "code": "NULL",
      "clientName": "NULL"
    },
    {
      "id": "72",
      "name": "Doc Test Project 1773074292973",
      "code": "NULL",
      "clientName": "NULL"
    },
    {
      "id": "30001",
      "name": "Test Project 1773104535085",
      "code": "TP-001",
      "clientName": "Test Client"
    },
    {
      "id": "30002",
      "name": "GetById Test 1773104535335",
      "code": "NULL",
      "clientName": "NULL"
    },
    {
      "id": "30005",
      "name": "Task Test Project 1773104538092",
      "code": "NULL",
      "clientName": "NULL"
    },
    {
      "id": "30006",
      "name": "Task Test Project 1773104538574",
      "code": "NULL",
      "clientName": "NULL"
    },
    {
      "id": "30007",
      "name": "Task Test Project 1773104539050",
      "code": "NULL",
      "clientName": "NULL"
    },
    {
      "id": "30008",
      "name": "Task Test Project 1773104539281",
      "code": "NULL",
      "clientName": "NULL"
    },
    {
      "id": "30009",
      "name": "Task Test Project 1773104539975",
      "code": "NULL",
      "clientName": "NULL"
    },
    {
      "id": "30010",
      "name": "Doc Test Project 1773104540899",
      "code": "NULL",
      "clientName": "NULL"
    },
    {
      "id": "30011",
      "name": "Doc Test Project 1773104541355",
      "code": "NULL",
      "clientName": "NULL"
    },
    {
      "id": "30012",
      "name": "Doc Test Project 1773104541831",
      "code": "NULL",
      "clientName": "NULL"
    },
    {
      "id": "30013",
      "name": "Test Project 1773104634430",
      "code": "TP-001",
      "clientName": "Test Client"
    },
    {
      "id": "30014",
      "name": "GetById Test 1773104634673",
      "code": "NULL",
      "clientName": "NULL"
    },
    {
      "id": "30017",
      "name": "Task Test Project 1773104637492",
      "code": "NULL",
      "clientName": "NULL"
    },
    {
      "id": "30018",
      "name": "Task Test Project 1773104637963",
      "code": "NULL",
      "clientName": "NULL"
    },
    {
      "id": "30019",
      "name": "Task Test Project 1773104638442",
      "code": "NULL",
      "clientName": "NULL"
    },
    {
      "id": "30020",
      "name": "Task Test Project 1773104638683",
      "code": "NULL",
      "clientName": "NULL"
    },
    {
      "id": "30021",
      "name": "Task Test Project 1773104639404",
      "code": "NULL",
      "clientName": "NULL"
    },
    {
      "id": "30022",
      "name": "Doc Test Project 1773104640350",
      "code": "NULL",
      "clientName": "NULL"
    },
    {
      "id": "30023",
      "name": "Doc Test Project 1773104640824",
      "code": "NULL",
      "clientName": "NULL"
    },
    {
      "id": "30024",
      "name": "Doc Test Project 1773104641302",
      "code": "NULL",
      "clientName": "NULL"
    },
    {
      "id": "30025",
      "name": "Test Project 1773105938071",
      "code": "TP-001",
      "clientName": "Test Client"
    },
    {
      "id": "30026",
      "name": "GetById Test 1773105938306",
      "code": "NULL",
      "clientName": "NULL"
    },
    {
      "id": "30029",
      "name": "Task Test Project 1773105941073",
      "code": "NULL",
      "clientName": "NULL"
    },
    {
      "id": "30030",
      "name": "Task Test Project 1773105941539",
      "code": "NULL",
      "clientName": "NULL"
    },
    {
      "id": "30031",
      "name": "Task Test Project 1773105942010",
      "code": "NULL",
      "clientName": "NULL"
    },
    {
      "id": "30032",
      "name": "Task Test Project 1773105942247",
      "code": "NULL",
      "clientName": "NULL"
    },
    {
      "id": "30033",
      "name": "Task Test Project 1773105942954",
      "code": "NULL",
      "clientName": "NULL"
    },
    {
      "id": "30034",
      "name": "Doc Test Project 1773105943881",
      "code": "NULL",
      "clientName": "NULL"
    },
    {
      "id": "30035",
      "name": "Doc Test Project 1773105944339",
      "code": "NULL",
      "clientName": "NULL"
    },
    {
      "id": "30036",
      "name": "Doc Test Project 1773105944806",
      "code": "NULL",
      "clientName": "NULL"
    },
    {
      "id": "30037",
      "name": "Test Project 1773106460434",
      "code": "TP-001",
      "clientName": "Test Client"
    },
    {
      "id": "30038",
      "name": "GetById Test 1773106460675",
      "code": "NULL",
      "clientName": "NULL"
    },
    {
      "id": "30041",
      "name": "Task Test Project 1773106463490",
      "code": "NULL",
      "clientName": "NULL"
    },
    {
      "id": "30042",
      "name": "Task Test Project 1773106463959",
      "code": "NULL",
      "clientName": "NULL"
    },
    {
      "id": "30043",
      "name": "Task Test Project 1773106464436",
      "code": "NULL",
      "clientName": "NULL"
    },
    {
      "id": "30044",
      "name": "Task Test Project 1773106464673",
      "code": "NULL",
      "clientName": "NULL"
    },
    {
      "id": "30045",
      "name": "Task Test Project 1773106465387",
      "code": "NULL",
      "clientName": "NULL"
    },
    {
      "id": "30046",
      "name": "Doc Test Project 1773106466321",
      "code": "NULL",
      "clientName": "NULL"
    },
    {
      "id": "30047",
      "name": "Doc Test Project 1773106466786",
      "code": "NULL",
      "clientName": "NULL"
    },
    {
      "id": "30048",
      "name": "Doc Test Project 1773106467258",
      "code": "NULL",
      "clientName": "NULL"
    },
    {
      "id": "30049",
      "name": "Test Project 1773106505468",
      "code": "TP-001",
      "clientName": "Test Client"
    },
    {
      "id": "30050",
      "name": "GetById Test 1773106505704",
      "code": "NULL",
      "clientName": "NULL"
    },
    {
      "id": "30053",
      "name": "Task Test Project 1773106508426",
      "code": "NULL",
      "clientName": "NULL"
    },
    {
      "id": "30054",
      "name": "Task Test Project 1773106508880",
      "code": "NULL",
      "clientName": "NULL"
    },
    {
      "id": "30055",
      "name": "Task Test Project 1773106509352",
      "code": "NULL",
      "clientName": "NULL"
    },
    {
      "id": "30056",
      "name": "Task Test Project 1773106509581",
      "code": "NULL",
      "clientName": "NULL"
    },
    {
      "id": "30057",
      "name": "Task Test Project 1773106510271",
      "code": "NULL",
      "clientName": "NULL"
    },
    {
      "id": "30058",
      "name": "Doc Test Project 1773106511195",
      "code": "NULL",
      "clientName": "NULL"
    },
    {
      "id": "30059",
      "name": "Doc Test Project 1773106511651",
      "code": "NULL",
      "clientName": "NULL"
    },
    {
      "id": "30060",
      "name": "Doc Test Project 1773106512113",
      "code": "NULL",
      "clientName": "NULL"
    },
    {
      "id": "30061",
      "name": "Test Project 1773107969588",
      "code": "TP-001",
      "clientName": "Test Client"
    },
    {
      "id": "30062",
      "name": "GetById Test 1773107969820",
      "code": "NULL",
      "clientName": "NULL"
    },
    {
      "id": "30065",
      "name": "Task Test Project 1773107972534",
      "code": "NULL",
      "clientName": "NULL"
    },
    {
      "id": "30066",
      "name": "Task Test Project 1773107972984",
      "code": "NULL",
      "clientName": "NULL"
    },
    {
      "id": "30067",
      "name": "Task Test Project 1773107973441",
      "code": "NULL",
      "clientName": "NULL"
    },
    {
      "id": "30068",
      "name": "Task Test Project 1773107973670",
      "code": "NULL",
      "clientName": "NULL"
    },
    {
      "id": "30069",
      "name": "Task Test Project 1773107974351",
      "code": "NULL",
      "clientName": "NULL"
    },
    {
      "id": "30070",
      "name": "Doc Test Project 1773107975252",
      "code": "NULL",
      "clientName": "NULL"
    },
    {
      "id": "30071",
      "name": "Doc Test Project 1773107975705",
      "code": "NULL",
      "clientName": "NULL"
    },
    {
      "id": "30072",
      "name": "Doc Test Project 1773107976160",
      "code": "NULL",
      "clientName": "NULL"
    },
    {
      "id": "30073",
      "name": "Test Project 1773108046957",
      "code": "TP-001",
      "clientName": "Test Client"
    },
    {
      "id": "30074",
      "name": "GetById Test 1773108047241",
      "code": "NULL",
      "clientName": "NULL"
    },
    {
      "id": "30077",
      "name": "Task Test Project 1773108049936",
      "code": "NULL",
      "clientName": "NULL"
    },
    {
      "id": "30078",
      "name": "Task Test Project 1773108050387",
      "code": "NULL",
      "clientName": "NULL"
    },
    {
      "id": "30079",
      "name": "Task Test Project 1773108050839",
      "code": "NULL",
      "clientName": "NULL"
    },
    {
      "id": "30080",
      "name": "Task Test Project 1773108051069",
      "code": "NULL",
      "clientName": "NULL"
    },
    {
      "id": "30081",
      "name": "Task Test Project 1773108051760",
      "code": "NULL",
      "clientName": "NULL"
    },
    {
      "id": "30082",
      "name": "Doc Test Project 1773108052670",
      "code": "NULL",
      "clientName": "NULL"
    },
    {
      "id": "30083",
      "name": "Doc Test Project 1773108053122",
      "code": "NULL",
      "clientName": "NULL"
    },
    {
      "id": "30084",
      "name": "Doc Test Project 1773108053582",
      "code": "NULL",
      "clientName": "NULL"
    },
    {
      "id": "30086",
      "name": "Test Project 1773109167370",
      "code": "TP-001",
      "clientName": "Test Client"
    },
    {
      "id": "30087",
      "name": "GetById Test 1773109167608",
      "code": "NULL",
      "clientName": "NULL"
    },
    {
      "id": "30090",
      "name": "Task Test Project 1773109170370",
      "code": "NULL",
      "clientName": "NULL"
    },
    {
      "id": "30091",
      "name": "Task Test Project 1773109170832",
      "code": "NULL",
      "clientName": "NULL"
    },
    {
      "id": "30092",
      "name": "Task Test Project 1773109171306",
      "code": "NULL",
      "clientName": "NULL"
    },
    {
      "id": "30093",
      "name": "Task Test Project 1773109171541",
      "code": "NULL",
      "clientName": "NULL"
    },
    {
      "id": "30094",
      "name": "Task Test Project 1773109172248",
      "code": "NULL",
      "clientName": "NULL"
    },
    {
      "id": "30095",
      "name": "Doc Test Project 1773109173182",
      "code": "NULL",
      "clientName": "NULL"
    },
    {
      "id": "30096",
      "name": "Doc Test Project 1773109173646",
      "code": "NULL",
      "clientName": "NULL"
    },
    {
      "id": "30097",
      "name": "Doc Test Project 1773109174121",
      "code": "NULL",
      "clientName": "NULL"
    },
    {
      "id": "30098",
      "name": "Test Project 1773109829173",
      "code": "TP-001",
      "clientName": "Test Client"
    },
    {
      "id": "30099",
      "name": "GetById Test 1773109829401",
      "code": "NULL",
      "clientName": "NULL"
    },
    {
      "id": "30102",
      "name": "Task Test Project 1773109832028",
      "code": "NULL",
      "clientName": "NULL"
    },
    {
      "id": "30103",
      "name": "Task Test Project 1773109832467",
      "code": "NULL",
      "clientName": "NULL"
    },
    {
      "id": "30104",
      "name": "Task Test Project 1773109832913",
      "code": "NULL",
      "clientName": "NULL"
    },
    {
      "id": "30105",
      "name": "Task Test Project 1773109833144",
      "code": "NULL",
      "clientName": "NULL"
    },
    {
      "id": "30106",
      "name": "Task Test Project 1773109833811",
      "code": "NULL",
      "clientName": "NULL"
    },
    {
      "id": "30107",
      "name": "Doc Test Project 1773109834700",
      "code": "NULL",
      "clientName": "NULL"
    },
    {
      "id": "30108",
      "name": "Doc Test Project 1773109835144",
      "code": "NULL",
      "clientName": "NULL"
    },
    {
      "id": "30109",
      "name": "Doc Test Project 1773109835591",
      "code": "NULL",
      "clientName": "NULL"
    },
    {
      "id": "30110",
      "name": "Test Project 1773110168079",
      "code": "TP-001",
      "clientName": "Test Client"
    },
    {
      "id": "30111",
      "name": "GetById Test 1773110168305",
      "code": "NULL",
      "clientName": "NULL"
    },
    {
      "id": "30114",
      "name": "Task Test Project 1773110170949",
      "code": "NULL",
      "clientName": "NULL"
    },
    {
      "id": "30115",
      "name": "Task Test Project 1773110171399",
      "code": "NULL",
      "clientName": "NULL"
    },
    {
      "id": "30116",
      "name": "Task Test Project 1773110171855",
      "code": "NULL",
      "clientName": "NULL"
    },
    {
      "id": "30117",
      "name": "Task Test Project 1773110172077",
      "code": "NULL",
      "clientName": "NULL"
    },
    {
      "id": "30118",
      "name": "Task Test Project 1773110172747",
      "code": "NULL",
      "clientName": "NULL"
    },
    {
      "id": "30119",
      "name": "Doc Test Project 1773110173624",
      "code": "NULL",
      "clientName": "NULL"
    },
    {
      "id": "30120",
      "name": "Doc Test Project 1773110174064",
      "code": "NULL",
      "clientName": "NULL"
    },
    {
      "id": "30121",
      "name": "Doc Test Project 1773110174509",
      "code": "NULL",
      "clientName": "NULL"
    },
    {
      "id": "30122",
      "name": "Test Project 1773111936295",
      "code": "TP-001",
      "clientName": "Test Client"
    },
    {
      "id": "30123",
      "name": "GetById Test 1773111936527",
      "code": "NULL",
      "clientName": "NULL"
    },
    {
      "id": "30126",
      "name": "Task Test Project 1773111939227",
      "code": "NULL",
      "clientName": "NULL"
    },
    {
      "id": "30127",
      "name": "Task Test Project 1773111939678",
      "code": "NULL",
      "clientName": "NULL"
    },
    {
      "id": "30128",
      "name": "Task Test Project 1773111940131",
      "code": "NULL",
      "clientName": "NULL"
    },
    {
      "id": "30129",
      "name": "Task Test Project 1773111940359",
      "code": "NULL",
      "clientName": "NULL"
    },
    {
      "id": "30130",
      "name": "Task Test Project 1773111941047",
      "code": "NULL",
      "clientName": "NULL"
    },
    {
      "id": "30131",
      "name": "Doc Test Project 1773111941949",
      "code": "NULL",
      "clientName": "NULL"
    },
    {
      "id": "30132",
      "name": "Doc Test Project 1773111942399",
      "code": "NULL",
      "clientName": "NULL"
    },
    {
      "id": "30133",
      "name": "Doc Test Project 1773111942852",
      "code": "NULL",
      "clientName": "NULL"
    },
    {
      "id": "30134",
      "name": "Test Project 1773112689938",
      "code": "TP-001",
      "clientName": "Test Client"
    },
    {
      "id": "30135",
      "name": "GetById Test 1773112690167",
      "code": "NULL",
      "clientName": "NULL"
    },
    {
      "id": "30138",
      "name": "Task Test Project 1773112692849",
      "code": "NULL",
      "clientName": "NULL"
    },
    {
      "id": "30139",
      "name": "Task Test Project 1773112693296",
      "code": "NULL",
      "clientName": "NULL"
    },
    {
      "id": "30140",
      "name": "Task Test Project 1773112693753",
      "code": "NULL",
      "clientName": "NULL"
    },
    {
      "id": "30141",
      "name": "Task Test Project 1773112693986",
      "code": "NULL",
      "clientName": "NULL"
    },
    {
      "id": "30142",
      "name": "Task Test Project 1773112694667",
      "code": "NULL",
      "clientName": "NULL"
    },
    {
      "id": "30143",
      "name": "Doc Test Project 1773112695576",
      "code": "NULL",
      "clientName": "NULL"
    },
    {
      "id": "30144",
      "name": "Doc Test Project 1773112696027",
      "code": "NULL",
      "clientName": "NULL"
    },
    {
      "id": "30145",
      "name": "Doc Test Project 1773112696487",
      "code": "NULL",
      "clientName": "NULL"
    },
    {
      "id": "30146",
      "name": "Test Project 1773112841370",
      "code": "TP-001",
      "clientName": "Test Client"
    },
    {
      "id": "30147",
      "name": "GetById Test 1773112841592",
      "code": "NULL",
      "clientName": "NULL"
    },
    {
      "id": "30150",
      "name": "Task Test Project 1773112844224",
      "code": "NULL",
      "clientName": "NULL"
    },
    {
      "id": "30151",
      "name": "Task Test Project 1773112844664",
      "code": "NULL",
      "clientName": "NULL"
    },
    {
      "id": "30152",
      "name": "Task Test Project 1773112845110",
      "code": "NULL",
      "clientName": "NULL"
    },
    {
      "id": "30153",
      "name": "Task Test Project 1773112845339",
      "code": "NULL",
      "clientName": "NULL"
    },
    {
      "id": "30154",
      "name": "Task Test Project 1773112846009",
      "code": "NULL",
      "clientName": "NULL"
    },
    {
      "id": "30155",
      "name": "Doc Test Project 1773112846896",
      "code": "NULL",
      "clientName": "NULL"
    },
    {
      "id": "30156",
      "name": "Doc Test Project 1773112847336",
      "code": "NULL",
      "clientName": "NULL"
    },
    {
      "id": "30157",
      "name": "Doc Test Project 1773112847783",
      "code": "NULL",
      "clientName": "NULL"
    },
    {
      "id": "60001",
      "name": "Test Project 1773155189643",
      "code": "TP-001",
      "clientName": "Test Client"
    },
    {
      "id": "60002",
      "name": "GetById Test 1773155189910",
      "code": "NULL",
      "clientName": "NULL"
    },
    {
      "id": "60005",
      "name": "Task Test Project 1773155192723",
      "code": "NULL",
      "clientName": "NULL"
    },
    {
      "id": "60006",
      "name": "Task Test Project 1773155193190",
      "code": "NULL",
      "clientName": "NULL"
    },
    {
      "id": "60007",
      "name": "Task Test Project 1773155193677",
      "code": "NULL",
      "clientName": "NULL"
    },
    {
      "id": "60008",
      "name": "Task Test Project 1773155193911",
      "code": "NULL",
      "clientName": "NULL"
    },
    {
      "id": "60009",
      "name": "Task Test Project 1773155194629",
      "code": "NULL",
      "clientName": "NULL"
    },
    {
      "id": "60010",
      "name": "Doc Test Project 1773155195566",
      "code": "NULL",
      "clientName": "NULL"
    },
    {
      "id": "60011",
      "name": "Doc Test Project 1773155196032",
      "code": "NULL",
      "clientName": "NULL"
    },
    {
      "id": "60012",
      "name": "Doc Test Project 1773155196520",
      "code": "NULL",
      "clientName": "NULL"
    },
    {
      "id": "60013",
      "name": "Test Project 1773156542589",
      "code": "TP-001",
      "clientName": "Test Client"
    },
    {
      "id": "60014",
      "name": "GetById Test 1773156542834",
      "code": "NULL",
      "clientName": "NULL"
    },
    {
      "id": "60017",
      "name": "Task Test Project 1773156545642",
      "code": "NULL",
      "clientName": "NULL"
    },
    {
      "id": "60018",
      "name": "Task Test Project 1773156546112",
      "code": "NULL",
      "clientName": "NULL"
    },
    {
      "id": "60019",
      "name": "Task Test Project 1773156546590",
      "code": "NULL",
      "clientName": "NULL"
    },
    {
      "id": "60020",
      "name": "Task Test Project 1773156546831",
      "code": "NULL",
      "clientName": "NULL"
    },
    {
      "id": "60021",
      "name": "Task Test Project 1773156547548",
      "code": "NULL",
      "clientName": "NULL"
    },
    {
      "id": "60022",
      "name": "Doc Test Project 1773156548494",
      "code": "NULL",
      "clientName": "NULL"
    },
    {
      "id": "60023",
      "name": "Doc Test Project 1773156548965",
      "code": "NULL",
      "clientName": "NULL"
    },
    {
      "id": "60024",
      "name": "Doc Test Project 1773156549442",
      "code": "NULL",
      "clientName": "NULL"
    },
    {
      "id": "60025",
      "name": "Test Project 1773158811168",
      "code": "TP-001",
      "clientName": "Test Client"
    },
    {
      "id": "60026",
      "name": "GetById Test 1773158811399",
      "code": "NULL",
      "clientName": "NULL"
    },
    {
      "id": "60029",
      "name": "Task Test Project 1773158814145",
      "code": "NULL",
      "clientName": "NULL"
    },
    {
      "id": "60030",
      "name": "Task Test Project 1773158814605",
      "code": "NULL",
      "clientName": "NULL"
    },
    {
      "id": "60031",
      "name": "Task Test Project 1773158815077",
      "code": "NULL",
      "clientName": "NULL"
    },
    {
      "id": "60032",
      "name": "Task Test Project 1773158815315",
      "code": "NULL",
      "clientName": "NULL"
    },
    {
      "id": "60033",
      "name": "Task Test Project 1773158816029",
      "code": "NULL",
      "clientName": "NULL"
    },
    {
      "id": "60034",
      "name": "Doc Test Project 1773158816978",
      "code": "NULL",
      "clientName": "NULL"
    },
    {
      "id": "60035",
      "name": "Doc Test Project 1773158817436",
      "code": "NULL",
      "clientName": "NULL"
    },
    {
      "id": "60036",
      "name": "Doc Test Project 1773158817915",
      "code": "NULL",
      "clientName": "NULL"
    },
    {
      "id": "60037",
      "name": "Test Project 1773160039176",
      "code": "TP-001",
      "clientName": "Test Client"
    },
    {
      "id": "60038",
      "name": "GetById Test 1773160039412",
      "code": "NULL",
      "clientName": "NULL"
    },
    {
      "id": "60041",
      "name": "Task Test Project 1773160042201",
      "code": "NULL",
      "clientName": "NULL"
    },
    {
      "id": "60042",
      "name": "Task Test Project 1773160042668",
      "code": "NULL",
      "clientName": "NULL"
    },
    {
      "id": "60043",
      "name": "Task Test Project 1773160043141",
      "code": "NULL",
      "clientName": "NULL"
    },
    {
      "id": "60044",
      "name": "Task Test Project 1773160043397",
      "code": "NULL",
      "clientName": "NULL"
    },
    {
      "id": "60045",
      "name": "Task Test Project 1773160044126",
      "code": "NULL",
      "clientName": "NULL"
    },
    {
      "id": "60046",
      "name": "Doc Test Project 1773160045059",
      "code": "NULL",
      "clientName": "NULL"
    },
    {
      "id": "60047",
      "name": "Doc Test Project 1773160045523",
      "code": "NULL",
      "clientName": "NULL"
    },
    {
      "id": "60048",
      "name": "Doc Test Project 1773160045994",
      "code": "NULL",
      "clientName": "NULL"
    },
    {
      "id": "90001",
      "name": "Test Project 1773162925918",
      "code": "TP-001",
      "clientName": "Test Client"
    },
    {
      "id": "90002",
      "name": "GetById Test 1773162926161",
      "code": "NULL",
      "clientName": "NULL"
    },
    {
      "id": "90005",
      "name": "Task Test Project 1773162928892",
      "code": "NULL",
      "clientName": "NULL"
    },
    {
      "id": "90006",
      "name": "Task Test Project 1773162929347",
      "code": "NULL",
      "clientName": "NULL"
    },
    {
      "id": "90007",
      "name": "Task Test Project 1773162929825",
      "code": "NULL",
      "clientName": "NULL"
    },
    {
      "id": "90008",
      "name": "Task Test Project 1773162930058",
      "code": "NULL",
      "clientName": "NULL"
    },
    {
      "id": "90009",
      "name": "Task Test Project 1773162930759",
      "code": "NULL",
      "clientName": "NULL"
    },
    {
      "id": "90010",
      "name": "Doc Test Project 1773162931682",
      "code": "NULL",
      "clientName": "NULL"
    },
    {
      "id": "90011",
      "name": "Doc Test Project 1773162932139",
      "code": "NULL",
      "clientName": "NULL"
    },
    {
      "id": "90012",
      "name": "Doc Test Project 1773162932613",
      "code": "NULL",
      "clientName": "NULL"
    },
    {
      "id": "120001",
      "name": "Test Project 1773192614945",
      "code": "TP-001",
      "clientName": "Test Client"
    },
    {
      "id": "120002",
      "name": "GetById Test 1773192615182",
      "code": "NULL",
      "clientName": "NULL"
    },
    {
      "id": "120005",
      "name": "Task Test Project 1773192617780",
      "code": "NULL",
      "clientName": "NULL"
    },
    {
      "id": "120006",
      "name": "Task Test Project 1773192618217",
      "code": "NULL",
      "clientName": "NULL"
    },
    {
      "id": "120007",
      "name": "Task Test Project 1773192618666",
      "code": "NULL",
      "clientName": "NULL"
    },
    {
      "id": "120008",
      "name": "Task Test Project 1773192618889",
      "code": "NULL",
      "clientName": "NULL"
    },
    {
      "id": "120009",
      "name": "Task Test Project 1773192619552",
      "code": "NULL",
      "clientName": "NULL"
    },
    {
      "id": "120010",
      "name": "Doc Test Project 1773192620430",
      "code": "NULL",
      "clientName": "NULL"
    },
    {
      "id": "120011",
      "name": "Doc Test Project 1773192620866",
      "code": "NULL",
      "clientName": "NULL"
    },
    {
      "id": "120012",
      "name": "Doc Test Project 1773192621321",
      "code": "NULL",
      "clientName": "NULL"
    },
    {
      "id": "120013",
      "name": "Test Project 1773193229243",
      "code": "TP-001",
      "clientName": "Test Client"
    },
    {
      "id": "120014",
      "name": "GetById Test 1773193229476",
      "code": "NULL",
      "clientName": "NULL"
    },
    {
      "id": "120017",
      "name": "Task Test Project 1773193232200",
      "code": "NULL",
      "clientName": "NULL"
    },
    {
      "id": "120018",
      "name": "Task Test Project 1773193232657",
      "code": "NULL",
      "clientName": "NULL"
    },
    {
      "id": "120019",
      "name": "Task Test Project 1773193233121",
      "code": "NULL",
      "clientName": "NULL"
    },
    {
      "id": "120020",
      "name": "Task Test Project 1773193233355",
      "code": "NULL",
      "clientName": "NULL"
    },
    {
      "id": "120021",
      "name": "Task Test Project 1773193234055",
      "code": "NULL",
      "clientName": "NULL"
    },
    {
      "id": "120022",
      "name": "Doc Test Project 1773193234979",
      "code": "NULL",
      "clientName": "NULL"
    },
    {
      "id": "120023",
      "name": "Doc Test Project 1773193235436",
      "code": "NULL",
      "clientName": "NULL"
    },
    {
      "id": "120024",
      "name": "Doc Test Project 1773193235893",
      "code": "NULL",
      "clientName": "NULL"
    },
    {
      "id": "120025",
      "name": "Test Project 1773193606350",
      "code": "TP-001",
      "clientName": "Test Client"
    },
    {
      "id": "120026",
      "name": "GetById Test 1773193606585",
      "code": "NULL",
      "clientName": "NULL"
    },
    {
      "id": "120029",
      "name": "Task Test Project 1773193609294",
      "code": "NULL",
      "clientName": "NULL"
    },
    {
      "id": "120030",
      "name": "Task Test Project 1773193609747",
      "code": "NULL",
      "clientName": "NULL"
    },
    {
      "id": "120031",
      "name": "Task Test Project 1773193610204",
      "code": "NULL",
      "clientName": "NULL"
    },
    {
      "id": "120032",
      "name": "Task Test Project 1773193610433",
      "code": "NULL",
      "clientName": "NULL"
    },
    {
      "id": "120033",
      "name": "Task Test Project 1773193611122",
      "code": "NULL",
      "clientName": "NULL"
    },
    {
      "id": "120034",
      "name": "Doc Test Project 1773193612034",
      "code": "NULL",
      "clientName": "NULL"
    },
    {
      "id": "120035",
      "name": "Doc Test Project 1773193612488",
      "code": "NULL",
      "clientName": "NULL"
    },
    {
      "id": "120036",
      "name": "Doc Test Project 1773193612948",
      "code": "NULL",
      "clientName": "NULL"
    },
    {
      "id": "120037",
      "name": "Test Project 1773194820650",
      "code": "TP-001",
      "clientName": "Test Client"
    },
    {
      "id": "120038",
      "name": "GetById Test 1773194820900",
      "code": "NULL",
      "clientName": "NULL"
    },
    {
      "id": "120041",
      "name": "Task Test Project 1773194823816",
      "code": "NULL",
      "clientName": "NULL"
    },
    {
      "id": "120042",
      "name": "Task Test Project 1773194824304",
      "code": "NULL",
      "clientName": "NULL"
    },
    {
      "id": "120043",
      "name": "Task Test Project 1773194824796",
      "code": "NULL",
      "clientName": "NULL"
    },
    {
      "id": "120044",
      "name": "Task Test Project 1773194825043",
      "code": "NULL",
      "clientName": "NULL"
    },
    {
      "id": "120045",
      "name": "Task Test Project 1773194825779",
      "code": "NULL",
      "clientName": "NULL"
    },
    {
      "id": "120046",
      "name": "Doc Test Project 1773194826763",
      "code": "NULL",
      "clientName": "NULL"
    },
    {
      "id": "120047",
      "name": "Doc Test Project 1773194827282",
      "code": "NULL",
      "clientName": "NULL"
    },
    {
      "id": "120048",
      "name": "Doc Test Project 1773194827774",
      "code": "NULL",
      "clientName": "NULL"
    },
    {
      "id": "150001",
      "name": "Test Project 1773199892538",
      "code": "TP-001",
      "clientName": "Test Client"
    },
    {
      "id": "150002",
      "name": "GetById Test 1773199892778",
      "code": "NULL",
      "clientName": "NULL"
    },
    {
      "id": "150005",
      "name": "Task Test Project 1773199895389",
      "code": "NULL",
      "clientName": "NULL"
    },
    {
      "id": "150006",
      "name": "Task Test Project 1773199895822",
      "code": "NULL",
      "clientName": "NULL"
    },
    {
      "id": "150007",
      "name": "Task Test Project 1773199896267",
      "code": "NULL",
      "clientName": "NULL"
    },
    {
      "id": "150008",
      "name": "Task Test Project 1773199896489",
      "code": "NULL",
      "clientName": "NULL"
    },
    {
      "id": "150009",
      "name": "Task Test Project 1773199897145",
      "code": "NULL",
      "clientName": "NULL"
    },
    {
      "id": "150010",
      "name": "Doc Test Project 1773199898011",
      "code": "NULL",
      "clientName": "NULL"
    },
    {
      "id": "150011",
      "name": "Doc Test Project 1773199898446",
      "code": "NULL",
      "clientName": "NULL"
    },
    {
      "id": "150012",
      "name": "Doc Test Project 1773199898888",
      "code": "NULL",
      "clientName": "NULL"
    },
    {
      "id": "150013",
      "name": "Test Project 1773200000724",
      "code": "TP-001",
      "clientName": "Test Client"
    },
    {
      "id": "150014",
      "name": "GetById Test 1773200000956",
      "code": "NULL",
      "clientName": "NULL"
    },
    {
      "id": "150017",
      "name": "Task Test Project 1773200003614",
      "code": "NULL",
      "clientName": "NULL"
    },
    {
      "id": "150018",
      "name": "Task Test Project 1773200004060",
      "code": "NULL",
      "clientName": "NULL"
    },
    {
      "id": "150019",
      "name": "Task Test Project 1773200004517",
      "code": "NULL",
      "clientName": "NULL"
    },
    {
      "id": "150020",
      "name": "Task Test Project 1773200004744",
      "code": "NULL",
      "clientName": "NULL"
    },
    {
      "id": "150021",
      "name": "Task Test Project 1773200005424",
      "code": "NULL",
      "clientName": "NULL"
    },
    {
      "id": "150022",
      "name": "Doc Test Project 1773200006329",
      "code": "NULL",
      "clientName": "NULL"
    },
    {
      "id": "150023",
      "name": "Doc Test Project 1773200006774",
      "code": "NULL",
      "clientName": "NULL"
    },
    {
      "id": "150024",
      "name": "Doc Test Project 1773200007231",
      "code": "NULL",
      "clientName": "NULL"
    },
    {
      "id": "150025",
      "name": "Test Project 1773201575143",
      "code": "TP-001",
      "clientName": "Test Client"
    },
    {
      "id": "150026",
      "name": "GetById Test 1773201575371",
      "code": "NULL",
      "clientName": "NULL"
    },
    {
      "id": "150029",
      "name": "Task Test Project 1773201578005",
      "code": "NULL",
      "clientName": "NULL"
    },
    {
      "id": "150030",
      "name": "Task Test Project 1773201578442",
      "code": "NULL",
      "clientName": "NULL"
    },
    {
      "id": "150031",
      "name": "Task Test Project 1773201578890",
      "code": "NULL",
      "clientName": "NULL"
    },
    {
      "id": "150032",
      "name": "Task Test Project 1773201579116",
      "code": "NULL",
      "clientName": "NULL"
    },
    {
      "id": "150033",
      "name": "Task Test Project 1773201579782",
      "code": "NULL",
      "clientName": "NULL"
    },
    {
      "id": "150034",
      "name": "Doc Test Project 1773201580671",
      "code": "NULL",
      "clientName": "NULL"
    },
    {
      "id": "150035",
      "name": "Doc Test Project 1773201581118",
      "code": "NULL",
      "clientName": "NULL"
    },
    {
      "id": "150036",
      "name": "Doc Test Project 1773201581565",
      "code": "NULL",
      "clientName": "NULL"
    },
    {
      "id": "150037",
      "name": "Test Project 1773202784808",
      "code": "TP-001",
      "clientName": "Test Client"
    },
    {
      "id": "150038",
      "name": "GetById Test 1773202785044",
      "code": "NULL",
      "clientName": "NULL"
    },
    {
      "id": "150041",
      "name": "Task Test Project 1773202787778",
      "code": "NULL",
      "clientName": "NULL"
    },
    {
      "id": "150042",
      "name": "Task Test Project 1773202788230",
      "code": "NULL",
      "clientName": "NULL"
    },
    {
      "id": "150043",
      "name": "Task Test Project 1773202788693",
      "code": "NULL",
      "clientName": "NULL"
    },
    {
      "id": "150044",
      "name": "Task Test Project 1773202788926",
      "code": "NULL",
      "clientName": "NULL"
    },
    {
      "id": "150045",
      "name": "Task Test Project 1773202789621",
      "code": "NULL",
      "clientName": "NULL"
    },
    {
      "id": "150046",
      "name": "Doc Test Project 1773202790540",
      "code": "NULL",
      "clientName": "NULL"
    },
    {
      "id": "150047",
      "name": "Doc Test Project 1773202790994",
      "code": "NULL",
      "clientName": "NULL"
    },
    {
      "id": "150048",
      "name": "Doc Test Project 1773202791459",
      "code": "NULL",
      "clientName": "NULL"
    },
    {
      "id": "150051",
      "name": "Test Project 1773205165563",
      "code": "TP-001",
      "clientName": "Test Client"
    },
    {
      "id": "150052",
      "name": "GetById Test 1773205165801",
      "code": "NULL",
      "clientName": "NULL"
    },
    {
      "id": "150055",
      "name": "Task Test Project 1773205168766",
      "code": "NULL",
      "clientName": "NULL"
    },
    {
      "id": "150056",
      "name": "Task Test Project 1773205169223",
      "code": "NULL",
      "clientName": "NULL"
    },
    {
      "id": "150057",
      "name": "Task Test Project 1773205169687",
      "code": "NULL",
      "clientName": "NULL"
    },
    {
      "id": "150058",
      "name": "Task Test Project 1773205169921",
      "code": "NULL",
      "clientName": "NULL"
    },
    {
      "id": "150059",
      "name": "Task Test Project 1773205170618",
      "code": "NULL",
      "clientName": "NULL"
    },
    {
      "id": "150060",
      "name": "Doc Test Project 1773205171545",
      "code": "NULL",
      "clientName": "NULL"
    },
    {
      "id": "150061",
      "name": "Doc Test Project 1773205172004",
      "code": "NULL",
      "clientName": "NULL"
    },
    {
      "id": "150062",
      "name": "Doc Test Project 1773205172472",
      "code": "NULL",
      "clientName": "NULL"
    }
  ],
  "messages": [],
  "stdout": "id\tname\tcode\tclientName\n1\tTest Project 1773068866475\tTP-001\tTest Client\n2\tGetById Test 1773068866727\tNULL\tNULL\n5\tTask Test Project 1773068869553\tNULL\tNULL\n6\tTask Test Project 1773068870025\tNULL\tNULL\n7\tTask Test Project 1773068870517\tNULL\tNULL\n8\tTask Test Project 1773068870757\tNULL\tNULL\n9\tTask Test Project 1773068871487\tNULL\tNULL\n10\tDoc Test Project 1773068872439\tNULL\tNULL\n11\tDoc Test Project 1773068872916\tNULL\tNULL\n12\tDoc Test Project 1773068873413\tNULL\tNULL\n13\tTest Project 1773070380255\tTP-001\tTest Client\n14\tGetById Test 1773070380495\tNULL\tNULL\n17\tTask Test Project 1773070383282\tNULL\tNULL\n18\tTask Test Project 1773070383755\tNULL\tNULL\n19\tTask Test Project 1773070384231\tNULL\tNULL\n20\tTask Test Project 1773070384470\tNULL\tNULL\n21\tTask Test Project 1773070385183\tNULL\tNULL\n22\tDoc Test Project 1773070386131\tNULL\tNULL\n23\tDoc Test Project 1773070386599\tNULL\tNULL\n24\tDoc Test Project 1773070387073\tNULL\tNULL\n25\tTest Project 1773070535847\tTP-001\tTest Client\n26\tGetById Test 1773070536096\tNULL\tNULL\n29\tTask Test Project 1773070539011\tNULL\tNULL\n30\tTask Test Project 1773070539496\tNULL\tNULL\n31\tTask Test Project 1773070539989\tNULL\tNULL\n32\tTask Test Project 1773070540237\tNULL\tNULL\n33\tTask Test Project 1773070540974\tNULL\tNULL\n34\tDoc Test Project 1773070541951\tNULL\tNULL\n35\tDoc Test Project 1773070542435\tNULL\tNULL\n36\tDoc Test Project 1773070542930\tNULL\tNULL\n37\tTest Project 1773072459505\tTP-001\tTest Client\n38\tGetById Test 1773072459758\tNULL\tNULL\n41\tTask Test Project 1773072462667\tNULL\tNULL\n42\tTask Test Project 1773072463151\tNULL\tNULL\n43\tTask Test Project 1773072463646\tNULL\tNULL\n44\tTask Test Project 1773072463895\tNULL\tNULL\n45\tTask Test Project 1773072464636\tNULL\tNULL\n46\tDoc Test Project 1773072465625\tNULL\tNULL\n47\tDoc Test Project 1773072466114\tNULL\tNULL\n48\tDoc Test Project 1773072466625\tNULL\tNULL\n49\tTest Project 1773072529749\tTP-001\tTest Client\n50\tGetById Test 1773072529990\tNULL\tNULL\n53\tTask Test Project 1773072532779\tNULL\tNULL\n54\tTask Test Project 1773072533246\tNULL\tNULL\n55\tTask Test Project 1773072533760\tNULL\tNULL\n56\tTask Test Project 1773072533999\tNULL\tNULL\n57\tTask Test Project 1773072534710\tNULL\tNULL\n58\tDoc Test Project 1773072535650\tNULL\tNULL\n59\tDoc Test Project 1773072536117\tNULL\tNULL\n60\tDoc Test Project 1773072536596\tNULL\tNULL\n61\tTest Project 1773074286220\tTP-001\tTest Client\n62\tGetById Test 1773074286458\tNULL\tNULL\n65\tTask Test Project 1773074289210\tNULL\tNULL\n66\tTask Test Project 1773074289668\tNULL\tNULL\n67\tTask Test Project 1773074290139\tNULL\tNULL\n68\tTask Test Project 1773074290373\tNULL\tNULL\n69\tTask Test Project 1773074291080\tNULL\tNULL\n70\tDoc Test Project 1773074292014\tNULL\tNULL\n71\tDoc Test Project 1773074292504\tNULL\tNULL\n72\tDoc Test Project 1773074292973\tNULL\tNULL\n30001\tTest Project 1773104535085\tTP-001\tTest Client\n30002\tGetById Test 1773104535335\tNULL\tNULL\n30005\tTask Test Project 1773104538092\tNULL\tNULL\n30006\tTask Test Project 1773104538574\tNULL\tNULL\n30007\tTask Test Project 1773104539050\tNULL\tNULL\n30008\tTask Test Project 1773104539281\tNULL\tNULL\n30009\tTask Test Project 1773104539975\tNULL\tNULL\n30010\tDoc Test Project 1773104540899\tNULL\tNULL\n30011\tDoc Test Project 1773104541355\tNULL\tNULL\n30012\tDoc Test Project 1773104541831\tNULL\tNULL\n30013\tTest Project 1773104634430\tTP-001\tTest Client\n30014\tGetById Test 1773104634673\tNULL\tNULL\n30017\tTask Test Project 1773104637492\tNULL\tNULL\n30018\tTask Test Project 1773104637963\tNULL\tNULL\n30019\tTask Test Project 1773104638442\tNULL\tNULL\n30020\tTask Test Project 1773104638683\tNULL\tNULL\n30021\tTask Test Project 1773104639404\tNULL\tNULL\n30022\tDoc Test Project 1773104640350\tNULL\tNULL\n30023\tDoc Test Project 1773104640824\tNULL\tNULL\n30024\tDoc Test Project 1773104641302\tNULL\tNULL\n30025\tTest Project 1773105938071\tTP-001\tTest Client\n30026\tGetById Test 1773105938306\tNULL\tNULL\n30029\tTask Test Project 1773105941073\tNULL\tNULL\n30030\tTask Test Project 1773105941539\tNULL\tNULL\n30031\tTask Test Project 1773105942010\tNULL\tNULL\n30032\tTask Test Project 1773105942247\tNULL\tNULL\n30033\tTask Test Project 1773105942954\tNULL\tNULL\n30034\tDoc Test Project 1773105943881\tNULL\tNULL\n30035\tDoc Test Project 1773105944339\tNULL\tNULL\n30036\tDoc Test Project 1773105944806\tNULL\tNULL\n30037\tTest Project 1773106460434\tTP-001\tTest Client\n30038\tGetById Test 1773106460675\tNULL\tNULL\n30041\tTask Test Project 1773106463490\tNULL\tNULL\n30042\tTask Test Project 1773106463959\tNULL\tNULL\n30043\tTask Test Project 1773106464436\tNULL\tNULL\n30044\tTask Test Project 1773106464673\tNULL\tNULL\n30045\tTask Test Project 1773106465387\tNULL\tNULL\n30046\tDoc Test Project 1773106466321\tNULL\tNULL\n30047\tDoc Test Project 1773106466786\tNULL\tNULL\n30048\tDoc Test Project 1773106467258\tNULL\tNULL\n30049\tTest Project 1773106505468\tTP-001\tTest Client\n30050\tGetById Test 1773106505704\tNULL\tNULL\n30053\tTask Test Project 1773106508426\tNULL\tNULL\n30054\tTask Test Project 1773106508880\tNULL\tNULL\n30055\tTask Test Project 1773106509352\tNULL\tNULL\n30056\tTask Test Project 1773106509581\tNULL\tNULL\n30057\tTask Test Project 1773106510271\tNULL\tNULL\n30058\tDoc Test Project 1773106511195\tNULL\tNULL\n30059\tDoc Test Project 1773106511651\tNULL\tNULL\n30060\tDoc Test Project 1773106512113\tNULL\tNULL\n30061\tTest Project 1773107969588\tTP-001\tTest Client\n30062\tGetById Test 1773107969820\tNULL\tNULL\n30065\tTask Test Project 1773107972534\tNULL\tNULL\n30066\tTask Test Project 1773107972984\tNULL\tNULL\n30067\tTask Test Project 1773107973441\tNULL\tNULL\n30068\tTask Test Project 1773107973670\tNULL\tNULL\n30069\tTask Test Project 1773107974351\tNULL\tNULL\n30070\tDoc Test Project 1773107975252\tNULL\tNULL\n30071\tDoc Test Project 1773107975705\tNULL\tNULL\n30072\tDoc Test Project 1773107976160\tNULL\tNULL\n30073\tTest Project 1773108046957\tTP-001\tTest Client\n30074\tGetById Test 1773108047241\tNULL\tNULL\n30077\tTask Test Project 1773108049936\tNULL\tNULL\n30078\tTask Test Project 1773108050387\tNULL\tNULL\n30079\tTask Test Project 1773108050839\tNULL\tNULL\n30080\tTask Test Project 1773108051069\tNULL\tNULL\n30081\tTask Test Project 1773108051760\tNULL\tNULL\n30082\tDoc Test Project 1773108052670\tNULL\tNULL\n30083\tDoc Test Project 1773108053122\tNULL\tNULL\n30084\tDoc Test Project 1773108053582\tNULL\tNULL\n30086\tTest Project 1773109167370\tTP-001\tTest Client\n30087\tGetById Test 1773109167608\tNULL\tNULL\n30090\tTask Test Project 1773109170370\tNULL\tNULL\n30091\tTask Test Project 1773109170832\tNULL\tNULL\n30092\tTask Test Project 1773109171306\tNULL\tNULL\n30093\tTask Test Project 1773109171541\tNULL\tNULL\n30094\tTask Test Project 1773109172248\tNULL\tNULL\n30095\tDoc Test Project 1773109173182\tNULL\tNULL\n30096\tDoc Test Project 1773109173646\tNULL\tNULL\n30097\tDoc Test Project 1773109174121\tNULL\tNULL\n30098\tTest Project 1773109829173\tTP-001\tTest Client\n30099\tGetById Test 1773109829401\tNULL\tNULL\n30102\tTask Test Project 1773109832028\tNULL\tNULL\n30103\tTask Test Project 1773109832467\tNULL\tNULL\n30104\tTask Test Project 1773109832913\tNULL\tNULL\n30105\tTask Test Project 1773109833144\tNULL\tNULL\n30106\tTask Test Project 1773109833811\tNULL\tNULL\n30107\tDoc Test Project 1773109834700\tNULL\tNULL\n30108\tDoc Test Project 1773109835144\tNULL\tNULL\n30109\tDoc Test Project 1773109835591\tNULL\tNULL\n30110\tTest Project 1773110168079\tTP-001\tTest Client\n30111\tGetById Test 1773110168305\tNULL\tNULL\n30114\tTask Test Project 1773110170949\tNULL\tNULL\n30115\tTask Test Project 1773110171399\tNULL\tNULL\n30116\tTask Test Project 1773110171855\tNULL\tNULL\n30117\tTask Test Project 1773110172077\tNULL\tNULL\n30118\tTask Test Project 1773110172747\tNULL\tNULL\n30119\tDoc Test Project 1773110173624\tNULL\tNULL\n30120\tDoc Test Project 1773110174064\tNULL\tNULL\n30121\tDoc Test Project 1773110174509\tNULL\tNULL\n30122\tTest Project 1773111936295\tTP-001\tTest Client\n30123\tGetById Test 1773111936527\tNULL\tNULL\n30126\tTask Test Project 1773111939227\tNULL\tNULL\n30127\tTask Test Project 1773111939678\tNULL\tNULL\n30128\tTask Test Project 1773111940131\tNULL\tNULL\n30129\tTask Test Project 1773111940359\tNULL\tNULL\n30130\tTask Test Project 1773111941047\tNULL\tNULL\n30131\tDoc Test Project 1773111941949\tNULL\tNULL\n30132\tDoc Test Project 1773111942399\tNULL\tNULL\n30133\tDoc Test Project 1773111942852\tNULL\tNULL\n30134\tTest Project 1773112689938\tTP-001\tTest Client\n30135\tGetById Test 1773112690167\tNULL\tNULL\n30138\tTask Test Project 1773112692849\tNULL\tNULL\n30139\tTask Test Project 1773112693296\tNULL\tNULL\n30140\tTask Test Project 1773112693753\tNULL\tNULL\n30141\tTask Test Project 1773112693986\tNULL\tNULL\n30142\tTask Test Project 1773112694667\tNULL\tNULL\n30143\tDoc Test Project 1773112695576\tNULL\tNULL\n30144\tDoc Test Project 1773112696027\tNULL\tNULL\n30145\tDoc Test Project 1773112696487\tNULL\tNULL\n30146\tTest Project 1773112841370\tTP-001\tTest Client\n30147\tGetById Test 1773112841592\tNULL\tNULL\n30150\tTask Test Project 1773112844224\tNULL\tNULL\n30151\tTask Test Project 1773112844664\tNULL\tNULL\n30152\tTask Test Project 1773112845110\tNULL\tNULL\n30153\tTask Test Project 1773112845339\tNULL\tNULL\n30154\tTask Test Project 1773112846009\tNULL\tNULL\n30155\tDoc Test Project 1773112846896\tNULL\tNULL\n30156\tDoc Test Project 1773112847336\tNULL\tNULL\n30157\tDoc Test Project 1773112847783\tNULL\tNULL\n60001\tTest Project 1773155189643\tTP-001\tTest Client\n60002\tGetById Test 1773155189910\tNULL\tNULL\n60005\tTask Test Project 1773155192723\tNULL\tNULL\n60006\tTask Test Project 1773155193190\tNULL\tNULL\n60007\tTask Test Project 1773155193677\tNULL\tNULL\n60008\tTask Test Project 1773155193911\tNULL\tNULL\n60009\tTask Test Project 1773155194629\tNULL\tNULL\n60010\tDoc Test Project 1773155195566\tNULL\tNULL\n60011\tDoc Test Project 1773155196032\tNULL\tNULL\n60012\tDoc Test Project 1773155196520\tNULL\tNULL\n60013\tTest Project 1773156542589\tTP-001\tTest Client\n60014\tGetById Test 1773156542834\tNULL\tNULL\n60017\tTask Test Project 1773156545642\tNULL\tNULL\n60018\tTask Test Project 1773156546112\tNULL\tNULL\n60019\tTask Test Project 1773156546590\tNULL\tNULL\n60020\tTask Test Project 1773156546831\tNULL\tNULL\n60021\tTask Test Project 1773156547548\tNULL\tNULL\n60022\tDoc Test Project 1773156548494\tNULL\tNULL\n60023\tDoc Test Project 1773156548965\tNULL\tNULL\n60024\tDoc Test Project 1773156549442\tNULL\tNULL\n60025\tTest Project 1773158811168\tTP-001\tTest Client\n60026\tGetById Test 1773158811399\tNULL\tNULL\n60029\tTask Test Project 1773158814145\tNULL\tNULL\n60030\tTask Test Project 1773158814605\tNULL\tNULL\n60031\tTask Test Project 1773158815077\tNULL\tNULL\n60032\tTask Test Project 1773158815315\tNULL\tNULL\n60033\tTask Test Project 1773158816029\tNULL\tNULL\n60034\tDoc Test Project 1773158816978\tNULL\tNULL\n60035\tDoc Test Project 1773158817436\tNULL\tNULL\n60036\tDoc Test Project 1773158817915\tNULL\tNULL\n60037\tTest Project 1773160039176\tTP-001\tTest Client\n60038\tGetById Test 1773160039412\tNULL\tNULL\n60041\tTask Test Project 1773160042201\tNULL\tNULL\n60042\tTask Test Project 1773160042668\tNULL\tNULL\n60043\tTask Test Project 1773160043141\tNULL\tNULL\n60044\tTask Test Project 1773160043397\tNULL\tNULL\n60045\tTask Test Project 1773160044126\tNULL\tNULL\n60046\tDoc Test Project 1773160045059\tNULL\tNULL\n60047\tDoc Test Project 1773160045523\tNULL\tNULL\n60048\tDoc Test Project 1773160045994\tNULL\tNULL\n90001\tTest Project 1773162925918\tTP-001\tTest Client\n90002\tGetById Test 1773162926161\tNULL\tNULL\n90005\tTask Test Project 1773162928892\tNULL\tNULL\n90006\tTask Test Project 1773162929347\tNULL\tNULL\n90007\tTask Test Project 1773162929825\tNULL\tNULL\n90008\tTask Test Project 1773162930058\tNULL\tNULL\n90009\tTask Test Project 1773162930759\tNULL\tNULL\n90010\tDoc Test Project 1773162931682\tNULL\tNULL\n90011\tDoc Test Project 1773162932139\tNULL\tNULL\n90012\tDoc Test Project 1773162932613\tNULL\tNULL\n120001\tTest Project 1773192614945\tTP-001\tTest Client\n120002\tGetById Test 1773192615182\tNULL\tNULL\n120005\tTask Test Project 1773192617780\tNULL\tNULL\n120006\tTask Test Project 1773192618217\tNULL\tNULL\n120007\tTask Test Project 1773192618666\tNULL\tNULL\n120008\tTask Test Project 1773192618889\tNULL\tNULL\n120009\tTask Test Project 1773192619552\tNULL\tNULL\n120010\tDoc Test Project 1773192620430\tNULL\tNULL\n120011\tDoc Test Project 1773192620866\tNULL\tNULL\n120012\tDoc Test Project 1773192621321\tNULL\tNULL\n120013\tTest Project 1773193229243\tTP-001\tTest Client\n120014\tGetById Test 1773193229476\tNULL\tNULL\n120017\tTask Test Project 1773193232200\tNULL\tNULL\n120018\tTask Test Project 1773193232657\tNULL\tNULL\n120019\tTask Test Project 1773193233121\tNULL\tNULL\n120020\tTask Test Project 1773193233355\tNULL\tNULL\n120021\tTask Test Project 1773193234055\tNULL\tNULL\n120022\tDoc Test Project 1773193234979\tNULL\tNULL\n120023\tDoc Test Project 1773193235436\tNULL\tNULL\n120024\tDoc Test Project 1773193235893\tNULL\tNULL\n120025\tTest Project 1773193606350\tTP-001\tTest Client\n120026\tGetById Test 1773193606585\tNULL\tNULL\n120029\tTask Test Project 1773193609294\tNULL\tNULL\n120030\tTask Test Project 1773193609747\tNULL\tNULL\n120031\tTask Test Project 1773193610204\tNULL\tNULL\n120032\tTask Test Project 1773193610433\tNULL\tNULL\n120033\tTask Test Project 1773193611122\tNULL\tNULL\n120034\tDoc Test Project 1773193612034\tNULL\tNULL\n120035\tDoc Test Project 1773193612488\tNULL\tNULL\n120036\tDoc Test Project 1773193612948\tNULL\tNULL\n120037\tTest Project 1773194820650\tTP-001\tTest Client\n120038\tGetById Test 1773194820900\tNULL\tNULL\n120041\tTask Test Project 1773194823816\tNULL\tNULL\n120042\tTask Test Project 1773194824304\tNULL\tNULL\n120043\tTask Test Project 1773194824796\tNULL\tNULL\n120044\tTask Test Project 1773194825043\tNULL\tNULL\n120045\tTask Test Project 1773194825779\tNULL\tNULL\n120046\tDoc Test Project 1773194826763\tNULL\tNULL\n120047\tDoc Test Project 1773194827282\tNULL\tNULL\n120048\tDoc Test Project 1773194827774\tNULL\tNULL\n150001\tTest Project 1773199892538\tTP-001\tTest Client\n150002\tGetById Test 1773199892778\tNULL\tNULL\n150005\tTask Test Project 1773199895389\tNULL\tNULL\n150006\tTask Test Project 1773199895822\tNULL\tNULL\n150007\tTask Test Project 1773199896267\tNULL\tNULL\n150008\tTask Test Project 1773199896489\tNULL\tNULL\n150009\tTask Test Project 1773199897145\tNULL\tNULL\n150010\tDoc Test Project 1773199898011\tNULL\tNULL\n150011\tDoc Test Project 1773199898446\tNULL\tNULL\n150012\tDoc Test Project 1773199898888\tNULL\tNULL\n150013\tTest Project 1773200000724\tTP-001\tTest Client\n150014\tGetById Test 1773200000956\tNULL\tNULL\n150017\tTask Test Project 1773200003614\tNULL\tNULL\n150018\tTask Test Project 1773200004060\tNULL\tNULL\n150019\tTask Test Project 1773200004517\tNULL\tNULL\n150020\tTask Test Project 1773200004744\tNULL\tNULL\n150021\tTask Test Project 1773200005424\tNULL\tNULL\n150022\tDoc Test Project 1773200006329\tNULL\tNULL\n150023\tDoc Test Project 1773200006774\tNULL\tNULL\n150024\tDoc Test Project 1773200007231\tNULL\tNULL\n150025\tTest Project 1773201575143\tTP-001\tTest Client\n150026\tGetById Test 1773201575371\tNULL\tNULL\n150029\tTask Test Project 1773201578005\tNULL\tNULL\n150030\tTask Test Project 1773201578442\tNULL\tNULL\n150031\tTask Test Project 1773201578890\tNULL\tNULL\n150032\tTask Test Project 1773201579116\tNULL\tNULL\n150033\tTask Test Project 1773201579782\tNULL\tNULL\n150034\tDoc Test Project 1773201580671\tNULL\tNULL\n150035\tDoc Test Project 1773201581118\tNULL\tNULL\n150036\tDoc Test Project 1773201581565\tNULL\tNULL\n150037\tTest Project 1773202784808\tTP-001\tTest Client\n150038\tGetById Test 1773202785044\tNULL\tNULL\n150041\tTask Test Project 1773202787778\tNULL\tNULL\n150042\tTask Test Project 1773202788230\tNULL\tNULL\n150043\tTask Test Project 1773202788693\tNULL\tNULL\n150044\tTask Test Project 1773202788926\tNULL\tNULL\n150045\tTask Test Project 1773202789621\tNULL\tNULL\n150046\tDoc Test Project 1773202790540\tNULL\tNULL\n150047\tDoc Test Project 1773202790994\tNULL\tNULL\n150048\tDoc Test Project 1773202791459\tNULL\tNULL\n150051\tTest Project 1773205165563\tTP-001\tTest Client\n150052\tGetById Test 1773205165801\tNULL\tNULL\n150055\tTask Test Project 1773205168766\tNULL\tNULL\n150056\tTask Test Project 1773205169223\tNULL\tNULL\n150057\tTask Test Project 1773205169687\tNULL\tNULL\n150058\tTask Test Project 1773205169921\tNULL\tNULL\n150059\tTask Test Project 1773205170618\tNULL\tNULL\n150060\tDoc Test Project 1773205171545\tNULL\tNULL\n150061\tDoc Test Project 1773205172004\tNULL\tNULL\n150062\tDoc Test Project 1773205172472\tNULL\tNULL\n",
  "stderr": "",
  "execution_time_ms": 1581
}